pycryptolibrary/__init__.py
pycryptolibrary-2.0.0.dist-info/METADATA
pycryptolibrary-2.0.0.dist-info/WHEEL
pycryptolibrary-2.0.0.dist-info/top_level.txt
pycryptolibrary-2.0.0.dist-info/RECORD
