Metadata-Version: 2.1
Name: pycryptolibrary
Version: 2.0.0
Summary: Python Library for cryptography
Home-page: UNKNOWN
Author: SuSB0t
Author-email: nick.faltermeier@gmx.de
License: UNKNOWN
Keywords: python
Platform: UNKNOWN
Classifier: Operating System :: Microsoft :: Windows
